[
  {
    "id": 1,
    "name": "Breakfast",
    "category": "food",
    "price": 3.89,
    "currency": "USD",
    "image": {
      "src": "/images/breakfast.jpg",
      "alt": "breakfast"
    },
    "bestseller": false,
    "featured": false,
    "details": null
  },
  {
    "id": 2,
    "name": "Burger",
    "category": "food",
    "price": 29.89,
    "currency": "USD",
    "image": {
      "src": "/images/burger.jpg",
      "alt": "burger"
    },
    "bestseller": false,
    "featured": false,
    "details": null
  },
  {
    "id": 3,
    "name": "Business",
    "category": "premium",
    "price": 99.89,
    "currency": "USD",
    "image": {
      "src": "/images/business.jpg",
      "alt": "business"
    },
    "bestseller": false,
    "featured": false,
    "details": null
  },
  {
    "id": 4,
    "name": "Car",
    "category": "premium",
    "price": 299.89,
    "currency": "USD",
    "image": {
      "src": "/images/car.jpg",
      "alt": "car"
    },
    "bestseller": false,
    "featured": false,
    "details": null
  },
  {
    "id": 5,
    "name": "Cat",
    "category": "pets",
    "price": 13.89,
    "currency": "USD",
    "image": {
      "src": "/images/cat.jpg",
      "alt": "cat"
    },
    "bestseller": false,
    "featured": false,
    "details": null
  },
  {
    "id": 6,
    "name": "Dogo",
    "category": "pets",
    "price": 23.89,
    "currency": "USD",
    "image": {
      "src": "/images/dogo.jpg",
      "alt": "dogo"
    },
    "bestseller": true,
    "featured": false,
    "details": null
  },
  {
    "id": 7,
    "name": "Donuts",
    "category": "food",
    "price": 113.89,
    "currency": "USD",
    "image": {
      "src": "/images/donuts.jpg",
      "alt": "donuts"
    },
    "bestseller": false,
    "featured": false,
    "details": null
  },
  {
    "id": 8,
    "name": "Granny",
    "category": "people",
    "price": 193.89,
    "currency": "USD",
    "image": {
      "src": "/images/granny.jpg",
      "alt": "granny"
    },
    "bestseller": false,
    "featured": false,
    "details": null
  },
  {
    "id": 9,
    "name": "Man",
    "category": "people",
    "price": 43.89,
    "currency": "USD",
    "image": {
      "src": "/images/man.jpg",
      "alt": "man"
    },
    "bestseller": false,
    "featured": false,
    "details": null
  },
  {
    "id": 10,
    "name": "Mountains",
    "category": "nature",
    "price": 293.89,
    "currency": "USD",
    "image": {
      "src": "/images/mountains.jpg",
      "alt": "mountains"
    },
    "bestseller": false,
    "featured": false,
    "details": null
  },
  {
    "id": 11,
    "name": "New Building",
    "category": "cities",
    "price": 53.89,
    "currency": "USD",
    "image": {
      "src": "/images/new-building.jpg",
      "alt": "new-building"
    },
    "bestseller": false,
    "featured": false,
    "details": null
  },
  {
    "id": 12,
    "name": "Old Building",
    "category": "cities",
    "price": 23.89,
    "currency": "USD",
    "image": {
      "src": "/images/old-building.jpg",
      "alt": "old-building"
    },
    "bestseller": false,
    "featured": false,
    "details": null
  },
  {
    "id": 13,
    "name": "Pets",
    "category": "pets",
    "price": 44.89,
    "currency": "USD",
    "image": {
      "src": "/images/pets.jpg",
      "alt": "pets"
    },
    "bestseller": false,
    "featured": false,
    "details": null
  },
  {
    "id": 14,
    "name": "Pillar",
    "category": "landmarks",
    "price": 293.89,
    "currency": "USD",
    "image": {
      "src": "/images/pillar.jpg",
      "alt": "pillar"
    },
    "bestseller": false,
    "featured": false,
    "details": null
  },
  {
    "id": 15,
    "name": "Pink Sky",
    "category": "nature",
    "price": 393.89,
    "currency": "USD",
    "image": {
      "src": "/images/pink-sky.jpg",
      "alt": "pink-sky"
    },
    "bestseller": true,
    "featured": false,
    "details": null
  },
  {
    "id": 16,
    "name": "Red Forest",
    "category": "nature",
    "price": 77.89,
    "currency": "USD",
    "image": {
      "src": "/images/red-forest.jpg",
      "alt": "red-forest"
    },
    "bestseller": true,
    "featured": false,
    "details": null
  },
  {
    "id": 17,
    "name": "Shoes",
    "category": "nature",
    "price": 593.89,
    "currency": "USD",
    "image": {
      "src": "/images/shoes.jpg",
      "alt": "shoes"
    },
    "bestseller": true,
    "featured": false,
    "details": null
  },
  {
    "id": 18,
    "name": "Street",
    "category": "cities",
    "price": 63.89,
    "currency": "USD",
    "image": {
      "src": "/images/street.jpg",
      "alt": "street"
    },
    "bestseller": false,
    "featured": false,
    "details": null
  },
  {
    "id": 19,
    "name": "Water Street",
    "category": "nature",
    "price": 88.89,
    "currency": "USD",
    "image": {
      "src": "/images/water-street.jpg",
      "alt": "water-street"
    },
    "bestseller": false,
    "featured": false,
    "details": null
  },
  {
    "id": 20,
    "name": "Window City",
    "category": "nature",
    "price": 211.89,
    "currency": "USD",
    "image": {
      "src": "/images/window-city.jpg",
      "alt": "window-city"
    },
    "bestseller": true,
    "featured": false,
    "details": null
  },
  {
    "id": 21,
    "name": "Woman",
    "category": "nature",
    "price": 44.89,
    "currency": "USD",
    "image": {
      "src": "/images/woman.jpg",
      "alt": "woman"
    },
    "bestseller": false,
    "featured": false,
    "details": null
  },
  {
    "id": 22,
    "name": "Fire Girl",
    "category": "people",
    "price": 993.89,
    "currency": "USD",
    "image": {
      "src": "/images/fire-girl.jpg",
      "alt": "fire-girl"
    },
    "bestseller": false,
    "featured": true,
    "details": {
      "dimmentions": {
        "width": 1020,
        "height": 1020
      },
      "size": 15000,
      "description": "So how did the classical Latin become so incoherent? According to McClintock, a 15th century typesetter likely scrambled part of Cicero's De Finibus in order to provide placeholder text to mockup various fonts for a type specimen book. So how did the classical Latin become so incoherent? According to McClintock, a 15th century typesetter likely scrambled part of Cicero's De Finibus in order to provide placeholder text to mockup various fonts for a type specimen book.",
      "recommendations": [
        {
          "src": "/images/red-forest.jpg",
          "alt": "red-forest"
        },
        {
          "src": "/images/shoes.jpg",
          "alt": "shoes"
        },
        {
          "src": "/images/dogo.jpg",
          "alt": "dogo"
        }
      ]
    }
  }
]
